py_semtools/__init__.py
py_semtools/cli_manager.py
py_semtools/main_modules.py
py_semtools/ontology.py
py_semtools/parallelizer.py
py_semtools/report_ont.py
py_semtools/sim_handler.py
py_semtools/stEngine.py
py_semtools/external_data/ontologies.txt
py_semtools/indexers/text_indexer.py
py_semtools/parsers/ont/file_parser.py
py_semtools/parsers/ont/json_parser.py
py_semtools/parsers/ont/oboparser.py
py_semtools/parsers/text/text_basic_parser.py
py_semtools/parsers/text/text_pubmed_abstract_parser.py
py_semtools/parsers/text/text_pubmed_paper_parser.py
py_semtools/parsers/text/text_pubmed_parser.py
py_semtools/templates/comorb_sugg.txt
py_semtools/templates/makeTermFreqTable.txt
py_semtools/templates/ontoICdist.txt
py_semtools/templates/ontodist.txt
py_semtools/templates/ontoplot.txt
py_semtools/templates/plotClust.txt
py_semtools/templates/plotProfRed.txt
py_semtools/templates/report.txt
py_semtools/templates/similarity_heatmap.txt
py_semtools/templates/similarity_matrix.txt
py_semtools/templates/stEngine.txt
py_semtools-1.3.1.dist-info/licenses/LICENSE.txt
py_semtools-1.3.1.dist-info/METADATA
py_semtools-1.3.1.dist-info/WHEEL
py_semtools-1.3.1.dist-info/entry_points.txt
py_semtools-1.3.1.dist-info/top_level.txt
py_semtools-1.3.1.dist-info/RECORD
